{
    "nom module":{
        "nom-menu-general" : "AI-tools",
        "action-generales":{
            "1": "creer",
            "2": "modifier"
        },
        "liste-des-actions-rapides":{
            "1": "4 : quitter le programme"
            
        },
        "nom fonction" : "nom fonction"
    },
        "entrées" : {
            "API-key" : "clef api gtp3.5",
            "choix-checkbox" : "Corrige moi le code suivant sans explication/Optimise moi le code suivant sans explication/Commente moi le code suivant sans explication/Quiter le programme",
            "entrez-votre-code" : "str du code a corriger"
        },
        "sortie" : {
            "sortie-possible" : "retour-console"
        },
        "erreur" : {
            "erreur-possible" : "retour-console"
        }
}



